iss_lidar/Lidar_functions.py
iss_lidar/__init__.py
iss_lidar/consensus_set.py
iss_lidar/halo_dl_decode.py
iss_lidar/ppi.py
iss_lidar/ppi_scans_to_vad.py
iss_lidar/tools.py
iss_lidar/vad.py
iss_lidar/vad_to_consensus.py
iss_lidar-1.2.3.dist-info/licenses/LICENSE
iss_lidar-1.2.3.dist-info/METADATA
iss_lidar-1.2.3.dist-info/WHEEL
iss_lidar-1.2.3.dist-info/entry_points.txt
iss_lidar-1.2.3.dist-info/top_level.txt
iss_lidar-1.2.3.dist-info/RECORD
