Metadata-Version: 2.4
Name: iss-lidar
Version: 1.2.3
Summary: Wind lidar processing library for the NSF NCAR Integrated Sounding System
Author-email: Isabel Suhr <isabels@ucar.edu>
Maintainer-email: Isabel Suhr <isabels@ucar.edu>
License: MIT License
Project-URL: Homepage, https://github.com/NCAR/iss-lidar
Project-URL: Issues, https://github.com/NCAR/iss-lidar/issues
Classifier: Programming Language :: Python :: 3
Classifier: License :: OSI Approved :: MIT License
Classifier: Operating System :: OS Independent
Requires-Python: >=3.8
License-File: LICENSE
Requires-Dist: matplotlib
Requires-Dist: netCDF4
Requires-Dist: numpy
Requires-Dist: pytz
Requires-Dist: scipy
Dynamic: license-file
